{
  "location": "WhitethorneLaunch",
  "sourceUrl": "https://www.aep.com/recreation/hydro/whitethornelaunch/",
  "sourceEndpoint": "https://aepcom-api.aep.com/api/hydro/forecast?location=WhitethorneLaunch",
  "generatedAt": "2026-03-18T12:45:38Z",
  "lastUpdated": "2026-03-18T08:45:00",
  "currentDateTime": 1773837938356,
  "waterReleasedHoursOffset": 8,
  "currentFlowCfs": 3836,
  "forecastCheckpoints": [
    {
      "label": "Now",
      "timestamp": 1773837938356,
      "flowCfs": 3836
    },
    {
      "label": "+1h",
      "timestamp": 1773841500000,
      "flowCfs": 4082
    },
    {
      "label": "+2h",
      "timestamp": 1773845100000,
      "flowCfs": 3843
    },
    {
      "label": "+4h",
      "timestamp": 1773852300000,
      "flowCfs": 3802
    },
    {
      "label": "+8h",
      "timestamp": 1773866700000,
      "flowCfs": 3689
    }
  ],
  "forecastPoints": [
    {
      "timestamp": 1773780300000,
      "flowCfs": 5673
    },
    {
      "timestamp": 1773781200000,
      "flowCfs": 5708
    },
    {
      "timestamp": 1773782100000,
      "flowCfs": 5849
    },
    {
      "timestamp": 1773783000000,
      "flowCfs": 5837
    },
    {
      "timestamp": 1773783900000,
      "flowCfs": 5799
    },
    {
      "timestamp": 1773784800000,
      "flowCfs": 5719
    },
    {
      "timestamp": 1773785700000,
      "flowCfs": 5855
    },
    {
      "timestamp": 1773786600000,
      "flowCfs": 5775
    },
    {
      "timestamp": 1773787500000,
      "flowCfs": 5666
    },
    {
      "timestamp": 1773788400000,
      "flowCfs": 5668
    },
    {
      "timestamp": 1773789300000,
      "flowCfs": 5847
    },
    {
      "timestamp": 1773790200000,
      "flowCfs": 5675
    },
    {
      "timestamp": 1773791100000,
      "flowCfs": 5764
    },
    {
      "timestamp": 1773792000000,
      "flowCfs": 5852
    },
    {
      "timestamp": 1773792900000,
      "flowCfs": 5666
    },
    {
      "timestamp": 1773793800000,
      "flowCfs": 5729
    },
    {
      "timestamp": 1773794700000,
      "flowCfs": 5818
    },
    {
      "timestamp": 1773795600000,
      "flowCfs": 5756
    },
    {
      "timestamp": 1773796500000,
      "flowCfs": 5809
    },
    {
      "timestamp": 1773797400000,
      "flowCfs": 6027
    },
    {
      "timestamp": 1773798300000,
      "flowCfs": 5758
    },
    {
      "timestamp": 1773799200000,
      "flowCfs": 5663
    },
    {
      "timestamp": 1773800100000,
      "flowCfs": 5679
    },
    {
      "timestamp": 1773801000000,
      "flowCfs": 6037
    },
    {
      "timestamp": 1773801900000,
      "flowCfs": 5940
    },
    {
      "timestamp": 1773802800000,
      "flowCfs": 5811
    },
    {
      "timestamp": 1773803700000,
      "flowCfs": 5821
    },
    {
      "timestamp": 1773804600000,
      "flowCfs": 5738
    },
    {
      "timestamp": 1773805500000,
      "flowCfs": 5723
    },
    {
      "timestamp": 1773806400000,
      "flowCfs": 5857
    },
    {
      "timestamp": 1773807300000,
      "flowCfs": 5729
    },
    {
      "timestamp": 1773808200000,
      "flowCfs": 5662
    },
    {
      "timestamp": 1773809100000,
      "flowCfs": 5783
    },
    {
      "timestamp": 1773810000000,
      "flowCfs": 5797
    },
    {
      "timestamp": 1773810900000,
      "flowCfs": 5995
    },
    {
      "timestamp": 1773811800000,
      "flowCfs": 5835
    },
    {
      "timestamp": 1773812700000,
      "flowCfs": 6093
    },
    {
      "timestamp": 1773813600000,
      "flowCfs": 5836
    },
    {
      "timestamp": 1773814500000,
      "flowCfs": 5765
    },
    {
      "timestamp": 1773815400000,
      "flowCfs": 5923
    },
    {
      "timestamp": 1773816300000,
      "flowCfs": 5922
    },
    {
      "timestamp": 1773817200000,
      "flowCfs": 3785
    },
    {
      "timestamp": 1773818100000,
      "flowCfs": 5864
    },
    {
      "timestamp": 1773819000000,
      "flowCfs": 6048
    },
    {
      "timestamp": 1773819900000,
      "flowCfs": 6002
    },
    {
      "timestamp": 1773820800000,
      "flowCfs": 4013
    },
    {
      "timestamp": 1773821700000,
      "flowCfs": 6023
    },
    {
      "timestamp": 1773822600000,
      "flowCfs": 5796
    },
    {
      "timestamp": 1773823500000,
      "flowCfs": 3836
    },
    {
      "timestamp": 1773824400000,
      "flowCfs": 3768
    },
    {
      "timestamp": 1773825300000,
      "flowCfs": 5761
    },
    {
      "timestamp": 1773826200000,
      "flowCfs": 5752
    },
    {
      "timestamp": 1773827100000,
      "flowCfs": 3801
    },
    {
      "timestamp": 1773828000000,
      "flowCfs": 3867
    },
    {
      "timestamp": 1773828900000,
      "flowCfs": 5841
    },
    {
      "timestamp": 1773829800000,
      "flowCfs": 5700
    },
    {
      "timestamp": 1773830700000,
      "flowCfs": 3772
    },
    {
      "timestamp": 1773831600000,
      "flowCfs": 3796
    },
    {
      "timestamp": 1773832500000,
      "flowCfs": 5864
    },
    {
      "timestamp": 1773833400000,
      "flowCfs": 5770
    },
    {
      "timestamp": 1773834300000,
      "flowCfs": 3816
    },
    {
      "timestamp": 1773835200000,
      "flowCfs": 3770
    },
    {
      "timestamp": 1773836100000,
      "flowCfs": 5837
    },
    {
      "timestamp": 1773837000000,
      "flowCfs": 5782
    },
    {
      "timestamp": 1773837900000,
      "flowCfs": 3830
    },
    {
      "timestamp": 1773838800000,
      "flowCfs": 3976
    },
    {
      "timestamp": 1773839700000,
      "flowCfs": 5931
    },
    {
      "timestamp": 1773840600000,
      "flowCfs": 5862
    },
    {
      "timestamp": 1773841500000,
      "flowCfs": 4082
    },
    {
      "timestamp": 1773842400000,
      "flowCfs": 3770
    },
    {
      "timestamp": 1773843300000,
      "flowCfs": 5839
    },
    {
      "timestamp": 1773844200000,
      "flowCfs": 5790
    },
    {
      "timestamp": 1773845100000,
      "flowCfs": 3843
    },
    {
      "timestamp": 1773846000000,
      "flowCfs": 3805
    },
    {
      "timestamp": 1773846900000,
      "flowCfs": 5788
    },
    {
      "timestamp": 1773847800000,
      "flowCfs": 5768
    },
    {
      "timestamp": 1773848700000,
      "flowCfs": 3716
    },
    {
      "timestamp": 1773849600000,
      "flowCfs": 4035
    },
    {
      "timestamp": 1773850500000,
      "flowCfs": 5803
    },
    {
      "timestamp": 1773851400000,
      "flowCfs": 5851
    },
    {
      "timestamp": 1773852300000,
      "flowCfs": 3802
    },
    {
      "timestamp": 1773853200000,
      "flowCfs": 3688
    },
    {
      "timestamp": 1773854100000,
      "flowCfs": 5786
    },
    {
      "timestamp": 1773855000000,
      "flowCfs": 5844
    },
    {
      "timestamp": 1773855900000,
      "flowCfs": 3714
    },
    {
      "timestamp": 1773856800000,
      "flowCfs": 3701
    },
    {
      "timestamp": 1773857700000,
      "flowCfs": 5852
    },
    {
      "timestamp": 1773858600000,
      "flowCfs": 3812
    },
    {
      "timestamp": 1773859500000,
      "flowCfs": 3718
    },
    {
      "timestamp": 1773860400000,
      "flowCfs": 3701
    },
    {
      "timestamp": 1773861300000,
      "flowCfs": 5888
    },
    {
      "timestamp": 1773862200000,
      "flowCfs": 3904
    },
    {
      "timestamp": 1773863100000,
      "flowCfs": 3829
    },
    {
      "timestamp": 1773864000000,
      "flowCfs": 3706
    },
    {
      "timestamp": 1773864900000,
      "flowCfs": 5839
    },
    {
      "timestamp": 1773865800000,
      "flowCfs": 3764
    },
    {
      "timestamp": 1773866700000,
      "flowCfs": 3689
    }
  ]
}
